Metadata-Version: 1.1
Name: django-sortedmanytomany
Version: 0.1.3
Summary: An extension of Django ManyToMany with ordering
Home-page: https://github.com/cereigido/django-sortedmanytomany/
Author: Paulo Cereigido
Author-email: paulocereigido@gmail.com
License: UNKNOWN
Download-URL: https://github.com/cereigido/django-sortedmanytomany//tarball/0.1.3
Platform: UNKNOWN
Classifier: Development Status :: 4 - Beta
Classifier: Environment :: Web Environment
Classifier: Framework :: Django
Classifier: Intended Audience :: Developers
Classifier: Intended Audience :: System Administrators
Classifier: License :: OSI Approved :: BSD License
Classifier: Operating System :: OS Independent
Classifier: Programming Language :: Python
Classifier: Topic :: Database
Classifier: Topic :: Internet :: WWW/HTTP
Classifier: Topic :: Internet :: WWW/HTTP :: Dynamic Content
Classifier: Topic :: Internet :: WWW/HTTP :: Site Management
Classifier: Topic :: Software Development :: Libraries :: Application Frameworks
Classifier: Topic :: Software Development :: Libraries :: Python Modules
